algoritma_optimal-0.1.0.dist-info/licenses/LICENSE
optimize_algorithm/__init__.py
optimize_algorithm/abc.py
optimize_algorithm/pso.py
algoritma_optimal-0.1.0.dist-info/METADATA
algoritma_optimal-0.1.0.dist-info/WHEEL
algoritma_optimal-0.1.0.dist-info/top_level.txt
algoritma_optimal-0.1.0.dist-info/RECORD
