Metadata-Version: 2.4
Name: algoritma_optimal
Version: 0.1.0
Summary: Kumpulan algoritma optimasi
Author: Muhamad Dimas Wijaya
Requires-Python: >=3.7
License-File: LICENSE
Requires-Dist: numpy
Requires-Dist: matplotlib
Dynamic: author
Dynamic: license-file
Dynamic: requires-dist
Dynamic: requires-python
Dynamic: summary
